ytpodgen/__init__.py
ytpodgen/downloader.py
ytpodgen/feedgenerator.py
ytpodgen/uploader.py
ytpodgen/ytpodgen.py
ytpodgen-0.3.2.dist-info/LICENSE
ytpodgen-0.3.2.dist-info/METADATA
ytpodgen-0.3.2.dist-info/WHEEL
ytpodgen-0.3.2.dist-info/entry_points.txt
ytpodgen-0.3.2.dist-info/RECORD
