Metadata-Version: 2.1
Name: ytpodgen
Version: 0.3.2
Summary: turns YouTube live streams into podcasts
Home-page: https://github.com/harupong/ytpodgen
License: MIT
Author: harupong
Author-email: harupong@gmail.com
Requires-Python: >=3.9,<4.0
Classifier: License :: OSI Approved :: MIT License
Classifier: Programming Language :: Python :: 3
Classifier: Programming Language :: Python :: 3.9
Classifier: Programming Language :: Python :: 3.10
Classifier: Programming Language :: Python :: 3.11
Requires-Dist: boto3 (>=1.26.89,<2.0.0)
Requires-Dist: click (>=8.1.3,<9.0.0)
Requires-Dist: loguru (>=0.6.0,<0.7.0)
Requires-Dist: podgen (>=1.1.0,<2.0.0)
Requires-Dist: requests (>=2.28.2,<3.0.0)
Requires-Dist: yt-dlp (>=2023.3.4,<2024.0.0)
Project-URL: Repository, https://github.com/harupong/ytpodgen
